x2vlm/Captioning_MLM.py
x2vlm/Grounding_bbox.py
x2vlm/MARVL.py
x2vlm/NLVR.py
x2vlm/Pretrain.py
x2vlm/Retrieval.py
x2vlm/VQA.py
x2vlm/VQA_msrvtt.py
x2vlm/VQA_msvd.py
x2vlm/WIT.py
x2vlm/XGQA.py
x2vlm/XRetrieval.py
x2vlm/XVNLI.py
x2vlm/__init__.py
x2vlm/optim.py
x2vlm/run.py
x2vlm/scheduler.py
x2vlm/xFlickrCO.py
x2vlm/accelerators/__init__.py
x2vlm/accelerators/accelerator.py
x2vlm/accelerators/apex_ddp_accelerator.py
x2vlm/dataset/__init__.py
x2vlm/dataset/captioning_dataset.py
x2vlm/dataset/dist_dataset.py
x2vlm/dataset/grounding_dataset.py
x2vlm/dataset/nlvr_dataset.py
x2vlm/dataset/pretrain_dataset.py
x2vlm/dataset/pretrain_dataset_multilingual.py
x2vlm/dataset/randaugment.py
x2vlm/dataset/retrieval_dataset.py
x2vlm/dataset/utils.py
x2vlm/dataset/vqa_dataset.py
x2vlm/dataset/wit_dataset.py
x2vlm/dataset/xflickrco_dataset.py
x2vlm/dataset/xvnli_dataset.py
x2vlm/dataset/tokenizers/__init__.py
x2vlm/dataset/tokenizers/bert_tokenizer_with_dropout.py
x2vlm/models/__init__.py
x2vlm/models/beit2.py
x2vlm/models/box_ops.py
x2vlm/models/clip_vit.py
x2vlm/models/model_classification.py
x2vlm/models/model_generation.py
x2vlm/models/model_grounding.py
x2vlm/models/model_pretrain.py
x2vlm/models/model_retrieval.py
x2vlm/models/resampler.py
x2vlm/models/swin_transformer.py
x2vlm/models/vit.py
x2vlm/models/xbert.py
x2vlm/models/xroberta.py
x2vlm/models/xvlm.py
x2vlm/refTools/__init__.py
x2vlm/refTools/refer_python3.py
x2vlm/refTools/evaluation/__init__.py
x2vlm/refTools/evaluation/refEvaluation.py
x2vlm/refTools/evaluation/bleu/__init__.py
x2vlm/refTools/evaluation/bleu/bleu.py
x2vlm/refTools/evaluation/bleu/bleu_scorer.py
x2vlm/refTools/evaluation/cider/__init__.py
x2vlm/refTools/evaluation/cider/cider.py
x2vlm/refTools/evaluation/cider/cider_scorer.py
x2vlm/refTools/evaluation/meteor/__init__.py
x2vlm/refTools/evaluation/meteor/meteor.py
x2vlm/refTools/evaluation/rouge/__init__.py
x2vlm/refTools/evaluation/rouge/rouge.py
x2vlm/refTools/evaluation/tokenizer/__init__.py
x2vlm_gml-0.1.1.dist-info/LICENSE
x2vlm_gml-0.1.1.dist-info/METADATA
x2vlm_gml-0.1.1.dist-info/WHEEL
x2vlm_gml-0.1.1.dist-info/top_level.txt
x2vlm_gml-0.1.1.dist-info/RECORD
